darkbuild/__init__.py
darkbuild/core/__init__.py
darkbuild/core/core.py
darkbuild/core/version.py
darkbuild/git/__init__.py
darkbuild/git/repo.py
darkbuild/manage/__init__.py
darkbuild/manage/core.py
darkbuild/manage/port.md
darkbuild/manage/supervisord.conf
darkbuild/shell/__init__.py
darkbuild/shell/core.py
darkbuild/temp/__init__.py
darkbuild/temp/core.json
darkbuild/temp/core.py
darkbuild/tool/__init__.py
darkbuild/tool/build.py
darkbuild/tool/fastapi.py
darkbuild-202303081522.dist-info/LICENSE
darkbuild-202303081522.dist-info/METADATA
darkbuild-202303081522.dist-info/WHEEL
darkbuild-202303081522.dist-info/entry_points.txt
darkbuild-202303081522.dist-info/top_level.txt
darkbuild-202303081522.dist-info/RECORD
