Metadata-Version: 2.1
Name: darkbuild
Version: 202303081522
Summary: darkbuild
Home-page: https://github.com/1007530194
Author: niuliangtao
Author-email: 1007530194@qq.com
License-File: LICENSE
Requires-Dist: GitPython
